voicecrypt/tests/test_core.py
voicecrypt/voicecrypt/__init__.py
voicecrypt/voicecrypt/core.py
aminulhoque-0.1.0.dist-info/METADATA
aminulhoque-0.1.0.dist-info/WHEEL
aminulhoque-0.1.0.dist-info/top_level.txt
aminulhoque-0.1.0.dist-info/RECORD
