Metadata-Version: 2.4
Name: aminulhoque
Version: 0.1.0
Summary: Encrypt and decrypt audio files as text for secure voice messaging.
Author-email: Aminul Hoque <aminul98547@gmail.com>
Requires-Python: >=3.7
Requires-Dist: cryptography>=41.0.0
